{
    " map_1 ": {
      " M ": {
        " bool_1 ": {
          " BOOL ": "true"
        },
        " number_1 ": {
          " N ": " -1.50 "
        },
        " null_1 ": {
          " NULL ": " true "
        },
        " string_1 ": {
          " S ": " 27509f16-3a5f-4789-a3fa-784498f11d91 "
        },
        " list_1 ": {
          " L ": [
            {
              " S ": " 27509f16-3a5f-4789-a3fa-784498f11d91 "
            },
            {
              "S": "2022-07-19T15:37:27-04:00"
            },
            {
              "S": ""
            },
            {
              " N ": " -1.50 "
            },
            {
              "N": "011"
            },
            {
              "N": "5215s"
            },
            {
              " BOOL ": " true "
            },
            {
              "BOOL": "false"
            },
            {
              "BOOL": "truthy"
            },
            {
              " NULL ": " true "
            },
            {
              " M ": {
                " bool_2 ": {
                  " BOOL ": "true"
                },
                " number_2 ": {
                  " N ": " -1.50 "
                },
                " null_2 ": {
                  " NULL ": " true "
                },
                " string_2 ": {
                  " S ": " 27509f16-3a5f-4789-a3fa-784498f11d91 "
                }
              }
            }
          ]
        },
        " map_2 ": {
          " M ": {
            " bool_3 ": {
              " BOOL ": "true"
            },
            " number_3 ": {
              " N ": " -1.50 "
            },
            " null_3 ": {
              " NULL ": " true "
            },
            " string_3 ": {
              " S ": " 27509f16-3a5f-4789-a3fa-784498f11d91 "
            },
            " map_3 ": {
              " M ": {
                " bool_4 ": {
                  " BOOL ": "true"
                },
                " number_4 ": {
                  " N ": " -1.50 "
                },
                " null_4 ": {
                  " NULL ": " true "
                },
                " string_4 ": {
                  " S ": " 27509f16-3a5f-4789-a3fa-784498f11d91 "
                }
              }
            }
          }
        }
      }
    },
    "map_4": {
      "M": "noop"
    },
    "map_5": {
      "M": {}
    },
    "map_6": {
      "M": {
        "noop": "noop"
      }
    },
    "map_7": "noop",
    "": {
      "M": {
        " bool_5 ": {
          " BOOL ": "true"
        }
      }
    }
  }